transports-0.1.2.dist-info/METADATA
transports-0.1.2.dist-info/WHEEL
transports-0.1.2.dist-info/license_files/LICENSE
transports/update.py
transports/server.py
transports/transport.py
transports/client.py
transports/tests/test_transport.py
transports/__init__.py
transports/model.py
transports/connection.py
transports/utils.py
transports/exceptions.py
transports/json.py
transports/handlers/starlette.py
transports/handlers/aiohttp_client.py
transports/handlers/__init__.py
transports/transports.abi3.so
transports-0.1.2.dist-info/RECORD
